[
  {
    "id": "DOC-1A42048E",
    "jobId": "2026020005",
    "folderId": null,
    "supplierId": null,
    "type": "technical_ROLE-02",
    "filename": "DOC-1A42048E_20260228171536.png",
    "originalName": "iş listesi görünüm.png",
    "path": "documents/teknik/DOC-1A42048E_20260228171536.png",
    "mimeType": "image/png",
    "size": 108395,
    "uploadedBy": "Sistem Yöneticisi",
    "uploadedAt": "2026-02-28T17:15:36.577990Z",
    "description": "Cam Balkon - Teknik Çizim"
  },
  {
    "id": "DOC-37B1118D",
    "jobId": "2026020005",
    "folderId": null,
    "supplierId": null,
    "type": "measure_ROLE-02",
    "filename": "DOC-37B1118D_20260228171530.png",
    "originalName": "iş listesi görünüm.png",
    "path": "documents/olcu/DOC-37B1118D_20260228171530.png",
    "mimeType": "image/png",
    "size": 108395,
    "uploadedBy": "Sistem Yöneticisi",
    "uploadedAt": "2026-02-28T17:15:30.362483Z",
    "description": "Cam Balkon - Ölçü Çizimi"
  },
  {
    "id": "DOC-54305BE8",
    "jobId": "2026020005",
    "folderId": null,
    "supplierId": null,
    "type": "technical_ROLE-01",
    "filename": "DOC-54305BE8_20260228171522.png",
    "originalName": "Ekran görüntüsü 2026-02-19 212030.png",
    "path": "documents/teknik/DOC-54305BE8_20260228171522.png",
    "mimeType": "image/png",
    "size": 213764,
    "uploadedBy": "Sistem Yöneticisi",
    "uploadedAt": "2026-02-28T17:15:22.521859Z",
    "description": "PVC Doğrama - Teknik Çizim"
  },
  {
    "id": "DOC-6B2E4C30",
    "jobId": "2026020005",
    "folderId": null,
    "supplierId": null,
    "type": "measure_ROLE-01",
    "filename": "DOC-6B2E4C30_20260228171518.png",
    "originalName": "Ekran görüntüsü 2026-02-19 212030.png",
    "path": "documents/olcu/DOC-6B2E4C30_20260228171518.png",
    "mimeType": "image/png",
    "size": 213764,
    "uploadedBy": "Sistem Yöneticisi",
    "uploadedAt": "2026-02-28T17:15:18.944158Z",
    "description": "PVC Doğrama - Ölçü Çizimi"
  },
  {
    "id": "DOC-BB71183A",
    "jobId": "2026020002",
    "folderId": null,
    "supplierId": null,
    "type": "montaj_oncesi",
    "filename": "DOC-BB71183A_20260220132627.png",
    "originalName": "Ekran görüntüsü 2026-02-19 212030.png",
    "path": "documents/montaj/DOC-BB71183A_20260220132627.png",
    "mimeType": "image/png",
    "size": 213764,
    "uploadedBy": "ebubekir altan",
    "uploadedAt": "2026-02-20T13:26:27.653340Z",
    "description": "Montaj öncesi fotoğraf"
  },
  {
    "id": "DOC-B54DAE7B",
    "jobId": "PO-PO-260220-001",
    "folderId": null,
    "supplierId": "SUP-A0F91ECF",
    "type": "irsaliye",
    "filename": "DOC-B54DAE7B_20260220113935.png",
    "originalName": "Ekran görüntüsü 2026-02-06 232634.png",
    "path": "documents/irsaliye/DOC-B54DAE7B_20260220113935.png",
    "mimeType": "image/png",
    "size": 138273,
    "uploadedBy": "Sistem Yöneticisi",
    "uploadedAt": "2026-02-20T11:39:35.309948Z",
    "description": "Teslimat İrsaliyesi - Artı Yapı - PO-260220-001 - 20.02.2026"
  },
  {
    "id": "DOC-6D675556",
    "jobId": "2026020002",
    "folderId": null,
    "supplierId": null,
    "type": "technical_ROLE-02",
    "filename": "DOC-6D675556_20260219160029.png",
    "originalName": "iş listesi görünüm.png",
    "path": "documents/teknik/DOC-6D675556_20260219160029.png",
    "mimeType": "image/png",
    "size": 108395,
    "uploadedBy": "Sistem Yöneticisi",
    "uploadedAt": "2026-02-19T16:00:29.384156Z",
    "description": "Cam Balkon - Teknik Çizim"
  },
  {
    "id": "DOC-C65C7E4D",
    "jobId": "2026020002",
    "folderId": null,
    "supplierId": null,
    "type": "measure_ROLE-02",
    "filename": "DOC-C65C7E4D_20260219160025.png",
    "originalName": "iş listesi görünüm.png",
    "path": "documents/olcu/DOC-C65C7E4D_20260219160025.png",
    "mimeType": "image/png",
    "size": 108395,
    "uploadedBy": "Sistem Yöneticisi",
    "uploadedAt": "2026-02-19T16:00:25.547228Z",
    "description": "Cam Balkon - Ölçü Çizimi"
  },
  {
    "id": "DOC-18B04D99",
    "jobId": "2026020002",
    "folderId": null,
    "supplierId": null,
    "type": "technical_ROLE-01",
    "filename": "DOC-18B04D99_20260219160021.png",
    "originalName": "iş listesi görünüm.png",
    "path": "documents/teknik/DOC-18B04D99_20260219160021.png",
    "mimeType": "image/png",
    "size": 108395,
    "uploadedBy": "Sistem Yöneticisi",
    "uploadedAt": "2026-02-19T16:00:21.391406Z",
    "description": "PVC Doğrama - Teknik Çizim"
  },
  {
    "id": "DOC-66059495",
    "jobId": "2026020002",
    "folderId": null,
    "supplierId": null,
    "type": "measure_ROLE-01",
    "filename": "DOC-66059495_20260219160017.png",
    "originalName": "iş listesi görünüm.png",
    "path": "documents/olcu/DOC-66059495_20260219160017.png",
    "mimeType": "image/png",
    "size": 108395,
    "uploadedBy": "Sistem Yöneticisi",
    "uploadedAt": "2026-02-19T16:00:17.217883Z",
    "description": "PVC Doğrama - Ölçü Çizimi"
  }
]